{
    "windows": [
        {
            "emotePopup": {
                "x": 362,
                "y": 490
            },
            "height": 1080,
            "tabs": [
                {
                    "highlightsEnabled": true,
                    "splits2": {
                        "data": {
                            "name": "pepega00000",
                            "type": "twitch"
                        },
                        "filters": [
                        ],
                        "flexh": 1,
                        "flexv": 1,
                        "moderationMode": false,
                        "type": "split"
                    },
                    "title": " "
                },
                {
                    "highlightsEnabled": true,
                    "splits2": {
                        "data": {
                            "name": "alte",
                            "type": "twitch"
                        },
                        "filters": [
                        ],
                        "flexh": 1,
                        "flexv": 1,
                        "moderationMode": false,
                        "type": "split"
                    },
                    "title": "A"
                },
                {
                    "highlightsEnabled": true,
                    "splits2": {
                        "data": {
                            "name": "btmc",
                            "type": "twitch"
                        },
                        "filters": [
                        ],
                        "flexh": 1,
                        "flexv": 1,
                        "moderationMode": false,
                        "type": "split"
                    },
                    "title": "B"
                },
                {
                    "highlightsEnabled": true,
                    "splits2": {
                        "data": {
                            "name": "elina",
                            "type": "twitch"
                        },
                        "filters": [
                        ],
                        "flexh": 1,
                        "flexv": 1,
                        "moderationMode": false,
                        "type": "split"
                    },
                    "title": "E"
                },
                {
                    "highlightsEnabled": true,
                    "splits2": {
                        "data": {
                            "name": "forsen",
                            "type": "twitch"
                        },
                        "filters": [
                        ],
                        "flexh": 1,
                        "flexv": 1,
                        "moderationMode": false,
                        "type": "split"
                    },
                    "title": "F"
                },
                {
                    "highlightsEnabled": true,
                    "splits2": {
                        "data": {
                            "name": "feinberg",
                            "type": "twitch"
                        },
                        "filters": [
                        ],
                        "flexh": 1,
                        "flexv": 1,
                        "moderationMode": false,
                        "type": "split"
                    },
                    "title": "F"
                },
                {
                    "highlightsEnabled": true,
                    "splits2": {
                        "data": {
                            "name": "gkey",
                            "type": "twitch"
                        },
                        "filters": [
                        ],
                        "flexh": 1,
                        "flexv": 1,
                        "moderationMode": false,
                        "type": "split"
                    },
                    "title": "G"
                },
                {
                    "highlightsEnabled": true,
                    "splits2": {
                        "data": {
                            "name": "hasanabi",
                            "type": "twitch"
                        },
                        "filters": [
                        ],
                        "flexh": 1,
                        "flexv": 1,
                        "moderationMode": false,
                        "type": "split"
                    },
                    "title": "H"
                },
                {
                    "highlightsEnabled": true,
                    "splits2": {
                        "data": {
                            "name": "igorcykel",
                            "type": "twitch"
                        },
                        "filters": [
                        ],
                        "flexh": 1,
                        "flexv": 1,
                        "moderationMode": false,
                        "type": "split"
                    },
                    "title": "I"
                },
                {
                    "highlightsEnabled": true,
                    "splits2": {
                        "data": {
                            "name": "jonbams",
                            "type": "twitch"
                        },
                        "filters": [
                        ],
                        "flexh": 1,
                        "flexv": 1,
                        "moderationMode": false,
                        "type": "split"
                    },
                    "title": "J"
                },
                {
                    "highlightsEnabled": true,
                    "splits2": {
                        "data": {
                            "name": "kattah",
                            "type": "twitch"
                        },
                        "filters": [
                        ],
                        "flexh": 1,
                        "flexv": 1,
                        "moderationMode": false,
                        "type": "split"
                    },
                    "title": "K"
                },
                {
                    "highlightsEnabled": true,
                    "splits2": {
                        "data": {
                            "name": "kodiak1777",
                            "type": "twitch"
                        },
                        "filters": [
                        ],
                        "flexh": 1,
                        "flexv": 1,
                        "moderationMode": false,
                        "type": "split"
                    },
                    "title": "K"
                },
                {
                    "highlightsEnabled": true,
                    "splits2": {
                        "data": {
                            "name": "marty_vole",
                            "type": "twitch"
                        },
                        "filters": [
                        ],
                        "flexh": 1,
                        "flexv": 1,
                        "moderationMode": false,
                        "type": "split"
                    },
                    "title": "M"
                },
                {
                    "highlightsEnabled": true,
                    "splits2": {
                        "data": {
                            "name": "moscowwbish",
                            "type": "twitch"
                        },
                        "filters": [
                        ],
                        "flexh": 1,
                        "flexv": 1,
                        "moderationMode": false,
                        "type": "split"
                    },
                    "title": "M"
                },
                {
                    "highlightsEnabled": true,
                    "splits2": {
                        "data": {
                            "name": "nymn",
                            "type": "twitch"
                        },
                        "filters": [
                        ],
                        "flexh": 1,
                        "flexv": 1,
                        "moderationMode": false,
                        "type": "split"
                    },
                    "title": "N"
                },
                {
                    "highlightsEnabled": true,
                    "splits2": {
                        "data": {
                            "name": "pajlada",
                            "type": "twitch"
                        },
                        "filters": [
                        ],
                        "flexh": 1,
                        "flexv": 1,
                        "moderationMode": false,
                        "type": "split"
                    },
                    "title": "P"
                },
                {
                    "highlightsEnabled": true,
                    "splits2": {
                        "data": {
                            "name": "pokelawls",
                            "type": "twitch"
                        },
                        "filters": [
                        ],
                        "flexh": 1,
                        "flexv": 1,
                        "moderationMode": false,
                        "type": "split"
                    },
                    "title": "P"
                },
                {
                    "highlightsEnabled": true,
                    "splits2": {
                        "data": {
                            "name": "pokimane",
                            "type": "twitch"
                        },
                        "filters": [
                        ],
                        "flexh": 1,
                        "flexv": 1,
                        "moderationMode": false,
                        "type": "split"
                    },
                    "title": "P"
                },
                {
                    "highlightsEnabled": true,
                    "selected": true,
                    "splits2": {
                        "data": {
                            "name": "supinic",
                            "type": "twitch"
                        },
                        "filters": [
                        ],
                        "flexh": 1,
                        "flexv": 1,
                        "moderationMode": false,
                        "type": "split"
                    },
                    "title": "S"
                },
                {
                    "highlightsEnabled": true,
                    "splits2": {
                        "data": {
                            "name": "trainwreckstv",
                            "type": "twitch"
                        },
                        "filters": [
                        ],
                        "flexh": 1,
                        "flexv": 1,
                        "moderationMode": false,
                        "type": "split"
                    },
                    "title": "T"
                },
                {
                    "highlightsEnabled": true,
                    "splits2": {
                        "data": {
                            "name": "vadikus007",
                            "type": "twitch"
                        },
                        "filters": [
                        ],
                        "flexh": 1,
                        "flexv": 1,
                        "moderationMode": false,
                        "type": "split"
                    },
                    "title": "V"
                },
                {
                    "highlightsEnabled": true,
                    "splits2": {
                        "data": {
                            "name": "wubbl0rz",
                            "type": "twitch"
                        },
                        "filters": [
                        ],
                        "flexh": 1,
                        "flexv": 1,
                        "moderationMode": false,
                        "type": "split"
                    },
                    "title": "W"
                },
                {
                    "highlightsEnabled": true,
                    "splits2": {
                        "data": {
                            "name": "xqc",
                            "type": "twitch"
                        },
                        "filters": [
                        ],
                        "flexh": 1,
                        "flexv": 1,
                        "moderationMode": false,
                        "type": "split"
                    },
                    "title": "X"
                },
                {
                    "highlightsEnabled": true,
                    "splits2": {
                        "data": {
                            "name": "zoil",
                            "type": "twitch"
                        },
                        "filters": [
                        ],
                        "flexh": 1,
                        "flexv": 1,
                        "moderationMode": false,
                        "type": "split"
                    },
                    "title": "Z"
                }
            ],
            "type": "main",
            "width": 370,
            "x": 1550,
            "y": 0
        }
    ]
}
